dehyphen/__init__.py
dehyphen/dehyphen.py
dehyphen/format.py
dehyphen/scorer.py
dehyphen-0.3.4.dist-info/LICENSE
dehyphen-0.3.4.dist-info/WHEEL
dehyphen-0.3.4.dist-info/METADATA
dehyphen-0.3.4.dist-info/RECORD
