Metadata-Version: 2.1
Name: dehyphen
Version: 0.3.4
Summary: Dehyphenation of broken text (mainly German), i.e., extracted from a PDF
Home-page: https://github.com/pd3f/dehyphen
License: GPL-3.0-only
Keywords: dehyphenation,nlp,german,hyhpens,pdf
Author: Johannes Filter
Author-email: hi@jfilter.de
Requires-Python: >=3.6
Classifier: License :: OSI Approved :: GNU General Public License v3 (GPLv3)
Classifier: Programming Language :: Python :: 3
Classifier: Programming Language :: Python :: 3.6
Classifier: Programming Language :: Python :: 3.7
Classifier: Programming Language :: Python :: 3.8
Classifier: Topic :: Scientific/Engineering :: Artificial Intelligence
Classifier: Topic :: Scientific/Engineering :: Information Analysis
Requires-Dist: clean-text[gpl]
Requires-Dist: pd3f-flair
Project-URL: Repository, https://github.com/pd3f/dehyphen
